{
  "replace": false,
  "values": [
    "minecraft:player",
    "minecraft:allay",
    "minecraft:armadillo",
    "minecraft:cat",
    "minecraft:cow",
    "minecraft:donkey",
    "minecraft:fox",
    "minecraft:hoglin",
    "minecraft:horse",
    "minecraft:iron_golem",
    "minecraft:llama",
    "minecraft:mule",
    "minecraft:ocelot",
    "minecraft:panda",
    "minecraft:pig",
    "minecraft:piglin",
    "minecraft:piglin_brute",
    "minecraft:pillager",
    "minecraft:polar_bear",
    "minecraft:rabbit",
    "minecraft:sheep",
    "minecraft:silverfish",
    "minecraft:slime",
    "minecraft:spider",
    "minecraft:villager",
    "minecraft:vindicator",
    "minecraft:wolf",
    {"id": "crystal_chronicles:crystal_wolf", "required": false },
    {"id": "crystal_chronicles:crystal_drake", "required": false },
    {"id": "crystal_chronicles:crystal_golem", "required": false },
    {"id": "crystal_chronicles:crystal_scorpion", "required": false },
    {"id": "eternal_starlight:boarwarf", "required": false },
    {"id": "eternal_starlight:ratlin", "required": false },
    {"id": "cataclysm:the_harbinger", "required": false },
    {"id": "cataclysm:the_prowler", "required": false },
    {"id": "cataclysm:the_watcher", "required": false },
    {"id": "traveloptics:summoned_the_watcher", "required": false},
    {"id": "bosses_of_mass_destruction:gauntlet", "required": false },
    "minecraft:bat",
    "minecraft:parrot",
    {"id": "alshanex_familiars:illusionist_pet", "required": false },
    {"id": "irons_spellbooks:archevoker", "required": false },
    {"id": "irons_spellbooks:summoned_polar_bear", "required": false},
    "minecraft:creeper",
    "minecraft:elder_guardian",
    "minecraft:evoker",
    "minecraft:guardian",
    "minecraft:ravager",
    "minecraft:trader_llama",
    "minecraft:vex",
    "minecraft:wandering_trader",
    {"id": "irons_spellbooks:citadel_keeper", "required": false }

  ]
}